[
  {
    "constant": true,
    "inputs": [
      {
        "name": "",
        "type": "uint256"
      }
    ],
    "name": "marketPairs",
    "outputs": [
      {
        "name": "name",
        "type": "string"
      },
      {
        "name": "feedAddress",
        "type": "address"
      },
      {
        "name": "decimal",
        "type": "uint256"
      },
      {
        "name": "totalRounds",
        "type": "uint256"
      }
    ],
    "payable": false,
    "stateMutability": "view",
    "type": "function"
  },
  {
    "constant": false,
    "inputs": [],
    "name": "renounceOwnership",
    "outputs": [],
    "payable": false,
    "stateMutability": "nonpayable",
    "type": "function"
  },
  {
    "constant": true,
    "inputs": [],
    "name": "owner",
    "outputs": [
      {
        "name": "",
        "type": "address"
      }
    ],
    "payable": false,
    "stateMutability": "view",
    "type": "function"
  },
  {
    "constant": true,
    "inputs": [],
    "name": "isOwner",
    "outputs": [
      {
        "name": "",
        "type": "bool"
      }
    ],
    "payable": false,
    "stateMutability": "view",
    "type": "function"
  },
  {
    "constant": true,
    "inputs": [
      {
        "name": "",
        "type": "uint256"
      }
    ],
    "name": "markets",
    "outputs": [
      {
        "name": "addr",
        "type": "address"
      }
    ],
    "payable": false,
    "stateMutability": "view",
    "type": "function"
  },
  {
    "constant": false,
    "inputs": [
      {
        "name": "newOwner",
        "type": "address"
      }
    ],
    "name": "transferOwnership",
    "outputs": [],
    "payable": false,
    "stateMutability": "nonpayable",
    "type": "function"
  },
  {
    "inputs": [],
    "payable": false,
    "stateMutability": "nonpayable",
    "type": "constructor"
  },
  {
    "anonymous": false,
    "inputs": [
      {
        "indexed": false,
        "name": "marketPair",
        "type": "uint256"
      },
      {
        "indexed": false,
        "name": "roundId",
        "type": "uint256"
      },
      {
        "indexed": false,
        "name": "marketAddress",
        "type": "address"
      }
    ],
    "name": "MarketCreated",
    "type": "event"
  },
  {
    "anonymous": false,
    "inputs": [
      {
        "indexed": true,
        "name": "previousOwner",
        "type": "address"
      },
      {
        "indexed": true,
        "name": "newOwner",
        "type": "address"
      }
    ],
    "name": "OwnershipTransferred",
    "type": "event"
  },
  {
    "constant": false,
    "inputs": [
      {
        "name": "_pair",
        "type": "uint256"
      }
    ],
    "name": "registerMarket",
    "outputs": [
      {
        "name": "",
        "type": "uint256"
      }
    ],
    "payable": false,
    "stateMutability": "nonpayable",
    "type": "function"
  },
  {
    "constant": false,
    "inputs": [
      {
        "name": "_pair",
        "type": "uint256"
      },
      {
        "name": "_startTime",
        "type": "uint256"
      },
      {
        "name": "_duration",
        "type": "uint256"
      }
    ],
    "name": "createMarket",
    "outputs": [],
    "payable": false,
    "stateMutability": "nonpayable",
    "type": "function"
  },
  {
    "constant": true,
    "inputs": [
      {
        "name": "_time",
        "type": "uint256"
      },
      {
        "name": "_pair",
        "type": "uint256"
      }
    ],
    "name": "getPairPrice",
    "outputs": [
      {
        "name": "",
        "type": "uint256"
      }
    ],
    "payable": false,
    "stateMutability": "view",
    "type": "function"
  },
  {
    "constant": true,
    "inputs": [
      {
        "name": "from",
        "type": "uint256"
      },
      {
        "name": "cnt",
        "type": "uint256"
      }
    ],
    "name": "getMarkets",
    "outputs": [
      {
        "name": "_markets",
        "type": "address[]"
      }
    ],
    "payable": false,
    "stateMutability": "view",
    "type": "function"
  },
  {
    "constant": false,
    "inputs": [],
    "name": "clearMarket",
    "outputs": [],
    "payable": false,
    "stateMutability": "nonpayable",
    "type": "function"
  },
  {
    "constant": true,
    "inputs": [],
    "name": "getRegistryData",
    "outputs": [
      {
        "name": "_nPairs",
        "type": "uint256"
      },
      {
        "name": "_time",
        "type": "uint256"
      }
    ],
    "payable": false,
    "stateMutability": "view",
    "type": "function"
  },
  {
    "constant": true,
    "inputs": [],
    "name": "getMarketList",
    "outputs": [
      {
        "name": "_markets",
        "type": "address[]"
      }
    ],
    "payable": false,
    "stateMutability": "view",
    "type": "function"
  },
  {
    "constant": true,
    "inputs": [],
    "name": "getCurrentTime",
    "outputs": [
      {
        "name": "",
        "type": "uint256"
      }
    ],
    "payable": false,
    "stateMutability": "view",
    "type": "function"
  }
]